antipywidgets/__init__.py
antipywidgets/jobs_runner.py
antipywidgets-0.0.4.dist-info/LICENSE
antipywidgets-0.0.4.dist-info/METADATA
antipywidgets-0.0.4.dist-info/WHEEL
antipywidgets-0.0.4.dist-info/top_level.txt
antipywidgets-0.0.4.dist-info/RECORD
