Metadata-Version: 2.1
Name: antipywidgets
Version: 0.0.4
Summary: My IPyWidgets
Home-page: https://github.com/IvanAntipov/AntIPyWidgets
Author: Ivan Antipov
License: UNKNOWN
Platform: UNKNOWN
Classifier: Programming Language :: Python :: 3
Classifier: License :: OSI Approved :: MIT License
Classifier: Operating System :: OS Independent
Requires-Python: >=3.7
License-File: LICENSE
Requires-Dist: ipywidgets (>=7.6.3)
